LICENSE
README.md
setup.py
fit_nbinom/__init__.py
fit_nbinom/fit_nbinom.py
fit_nbinom.egg-info/PKG-INFO
fit_nbinom.egg-info/SOURCES.txt
fit_nbinom.egg-info/dependency_links.txt
fit_nbinom.egg-info/requires.txt
fit_nbinom.egg-info/top_level.txt