Metadata-Version: 1.1
Name: fit-nbinom
Version: 1.1
Summary: Negative binomial maximum likelihood estimator.
Home-page: https://github.com/joachimwolff/fit_nbinom
Author: Gökçen Eraslan, Joachim Wolff
Author-email: wolffj@informatik.uni-freiburg.de
License: LICENSE.md
Platform: UNKNOWN
Classifier: Intended Audience :: Science/Research
Classifier: Topic :: Scientific/Engineering :: Bio-Informatics
